{
  "topic": "International trade barriers are being reduced worldwide. Do the advantages of globalization outweigh the disadvantages?",
  "essayText": "As trade barriers continue falling worldwide, globalization reshapes our economic and social landscapes. While this process creates both winners and losers, I believe the overall advantages outweigh the disadvantages for most people globally.\n\nThe benefits of globalization are substantial and wide-reaching. Consumers enjoy access to affordable products from around the world, from Japanese electronics to Italian fashion. This competition drives innovation and quality improvements. Developing countries gain opportunities to participate in global supply chains, creating millions of jobs. For instance, Southeast Asian nations have built thriving manufacturing sectors serving international markets. Additionally, globalization facilitates cultural exchange through travel, media, and cuisine, enriching our daily experiences. International cooperation on issues like climate change and health crises becomes more feasible when nations are economically connected.\n\nHowever, globalization also creates serious problems that cannot be ignored. Workers in developed countries face job losses as companies move operations overseas seeking cheaper labor. This has devastated many industrial communities. Small local businesses struggle to compete with global chains, leading to downtown areas filled with identical multinational brands. Income inequality has increased as skilled workers and capital owners benefit more than others. Environmental damage accelerates as production moves to countries with weaker protections.\n\nDespite these challenges, the net benefits remain positive. Hundreds of millions have escaped poverty through globalization. Technology transfer helps developing nations advance rapidly. The solution involves better policies to support displaced workers and environmental protection, not reversing globalization itself.\n\nIn conclusion, while globalization presents real challenges, its advantages in reducing poverty and fostering development outweigh the disadvantages when accompanied by appropriate support measures.",
  "wordCount": 260,
  "officialScore": 84,
  "scoreBreakdown": {
    "content": 3,
    "form": 1,
    "grammar": 2,
    "vocabulary": 2,
    "spelling": 1,
    "developmentCoherence": 2,
    "linguisticRange": 2
  },
  "strengths": [],
  "weaknesses": []
}